atlas_gen/__init__.py
atlas_gen/mesh_utils.py
atlas_gen/metadata.py
atlas_gen/metadata_utils.py
atlas_gen/stacks.py
atlas_gen/structure_json_to_csv.py
atlas_gen/structures.py
atlas_gen/volume_utils.py
atlas_gen/wrapup.py
atlas_gen/atlas_scripts/__init__.py
atlas_gen/atlas_scripts/allenbrain_atlas.py
atlas_gen/atlas_scripts/example_atlas.py
atlas_gen/atlas_scripts/fishatlas_atlas.py
atlas_gen/atlas_scripts/fishatlas_utils.py
atlas_gen/atlas_scripts/humanatlas.py
atlas_gen/atlas_scripts/kim_unified_atlas.py
atlas_gen/atlas_scripts/ratatlas.py
brainatlas_api/__init__.py
brainatlas_api/bg_atlas.py
brainatlas_api/core.py
brainatlas_api/descriptors.py
brainatlas_api/obj_utils.py
brainatlas_api/utils.py
brainatlas_api/structures/__init__.py
brainatlas_api/structures/simple_tree.py
brainatlas_api/structures/structure_tree.py
brainatlas_api-0.0.2rc0.dist-info/LICENSE
brainatlas_api-0.0.2rc0.dist-info/METADATA
brainatlas_api-0.0.2rc0.dist-info/WHEEL
brainatlas_api-0.0.2rc0.dist-info/top_level.txt
brainatlas_api-0.0.2rc0.dist-info/RECORD
